README.md
setup.py
s3vault/__init__.py
s3vault/tests.py
s3vault/vault.py
s3vault.egg-info/PKG-INFO
s3vault.egg-info/SOURCES.txt
s3vault.egg-info/dependency_links.txt
s3vault.egg-info/requires.txt
s3vault.egg-info/top_level.txt