Metadata-Version: 2.1
Name: s3vault
Version: 0.1.1
Summary: ...
Home-page: https://gitlab.com/.../...
Author: SchoolOrchestration
Author-email: tech@appointmentguru.co
License: UNKNOWN
Platform: UNKNOWN
Classifier: Programming Language :: Python :: 3
Classifier: Operating System :: OS Independent
